LICENSE
MANIFEST.in
README
ez_setup.py
setup.py
docs/Makefile
docs/breakingchanges.txt
docs/conf.py
docs/gettingstarted.txt
docs/index.txt
docs/installation.txt
docs/resource.txt
docs/_build/doctrees/breakingchanges.doctree
docs/_build/doctrees/environment.pickle
docs/_build/doctrees/gettingstarted.doctree
docs/_build/doctrees/index.doctree
docs/_build/doctrees/installation.doctree
docs/_build/doctrees/resource.doctree
docs/_build/doctrees/client/database.doctree
docs/_build/doctrees/client/index.doctree
docs/_build/doctrees/client/server.doctree
docs/_build/doctrees/client/view.doctree
docs/_build/doctrees/core/database.doctree
docs/_build/doctrees/core/index.doctree
docs/_build/doctrees/core/server.doctree
docs/_build/doctrees/core/view.doctree
docs/_build/doctrees/schema/creating_getting_deleting.doctree
docs/_build/doctrees/schema/document.doctree
docs/_build/doctrees/schema/index.doctree
docs/_build/doctrees/schema/property.doctree
docs/_build/html/breakingchanges.html
docs/_build/html/genindex.html
docs/_build/html/gettingstarted.html
docs/_build/html/index.html
docs/_build/html/installation.html
docs/_build/html/modindex.html
docs/_build/html/objects.inv
docs/_build/html/resource.html
docs/_build/html/search.html
docs/_build/html/searchindex.js
docs/_build/html/_sources/breakingchanges.txt
docs/_build/html/_sources/gettingstarted.txt
docs/_build/html/_sources/index.txt
docs/_build/html/_sources/installation.txt
docs/_build/html/_sources/resource.txt
docs/_build/html/_sources/client/database.txt
docs/_build/html/_sources/client/index.txt
docs/_build/html/_sources/client/server.txt
docs/_build/html/_sources/client/view.txt
docs/_build/html/_sources/core/database.txt
docs/_build/html/_sources/core/index.txt
docs/_build/html/_sources/core/server.txt
docs/_build/html/_sources/core/view.txt
docs/_build/html/_sources/schema/creating_getting_deleting.txt
docs/_build/html/_sources/schema/document.txt
docs/_build/html/_sources/schema/index.txt
py_simplecouchdb.egg-info/PKG-INFO
py_simplecouchdb.egg-info/SOURCES.txt
py_simplecouchdb.egg-info/dependency_links.txt
py_simplecouchdb.egg-info/not-zip-safe
py_simplecouchdb.egg-info/requires.txt
py_simplecouchdb.egg-info/top_level.txt
