Metadata-Version: 1.0
Name: py-simplecouchdb
Version: 0.9.26
Summary: Simple CouchDB library
Home-page: http://code.google.com/p/py-simplecouchdb/
Author: Benoit Chesneau
Author-email: benoitc@e-engura.com
License: Apache License 2
Platform: UNKNOWN
Classifier: Development Status :: 4 - Beta
Classifier: Environment :: Other Environment
Classifier: Intended Audience :: Developers
Classifier: License :: OSI Approved :: Apache Software License
Classifier: Operating System :: OS Independent
Classifier: Programming Language :: Python
Classifier: Topic :: Database
Classifier: Topic :: Utilities
Classifier: Topic :: Software Development :: Libraries :: Python Modules
